EspGetData/__init__.py
EspGetData/main.py
EspGetData-1.0.2.dist-info/METADATA
EspGetData-1.0.2.dist-info/WHEEL
EspGetData-1.0.2.dist-info/top_level.txt
EspGetData-1.0.2.dist-info/RECORD
