Metadata-Version: 2.1
Name: EspGetData
Version: 1.0.2
Requires-Dist: requests
